udata_croquemort/__init__.py
udata_croquemort/checker.py
udata_croquemort/commands.py
udata_croquemort/models.py
udata_croquemort/tests.py
udata_croquemort/utils.py
udata_croquemort.egg-info/PKG-INFO
udata_croquemort.egg-info/SOURCES.txt
udata_croquemort.egg-info/dependency_links.txt
udata_croquemort.egg-info/entry_points.txt
udata_croquemort.egg-info/requires.txt
udata_croquemort.egg-info/top_level.txt
udata_croquemort-2.0.1.dist-info/LICENSE
udata_croquemort-2.0.1.dist-info/METADATA
udata_croquemort-2.0.1.dist-info/WHEEL
udata_croquemort-2.0.1.dist-info/entry_points.txt
udata_croquemort-2.0.1.dist-info/top_level.txt
udata_croquemort-2.0.1.dist-info/RECORD
