Metadata-Version: 2.1
Name: udata-croquemort
Version: 2.0.1
Summary: Croquemort support for uData
Home-page: https://github.com/opendatateam/udata-croquemort
Author: Opendata Team
Author-email: opendatateam@data.gouv.fr
License: LGPL
Keywords: udata croquemort
Platform: UNKNOWN
Classifier: Development Status :: 3 - Alpha
Classifier: Programming Language :: Python
Classifier: Environment :: Web Environment
Classifier: Operating System :: OS Independent
Classifier: Intended Audience :: Developers
Classifier: Topic :: System :: Software Distribution
Classifier: Programming Language :: Python
Classifier: Programming Language :: Python :: 3
Classifier: Programming Language :: Python :: 3.7
Classifier: Topic :: Software Development :: Libraries :: Python Modules
Classifier: License :: OSI Approved :: GNU Library or Lesser General Public License (LGPL)
Requires-Python: >=3.7
Requires-Dist: udata (>=2.0.0)
Provides-Extra: test
Requires-Dist: httpretty (==0.9.6) ; extra == 'test'
Requires-Dist: mock (==2.0.0) ; extra == 'test'
Requires-Dist: pytest (==4.6.3) ; extra == 'test'
Requires-Dist: pytest-flask (==0.15.0) ; extra == 'test'
Requires-Dist: pytest-sugar (==0.9.2) ; extra == 'test'
